granturismo/__init__.py
granturismo/intake/__init__.py
granturismo/intake/listener.py
granturismo/maps/__init__.py
granturismo/maps/map.py
granturismo/model/__init__.py
granturismo/model/common.py
granturismo/model/packet.py
granturismo/security/__init__.py
granturismo/security/decrypter.py
granturismo/utils/__init__.py
granturismo/utils/debug.py
granturismo/utils/network_to_host.py
granturismo/utils/settings.py
granturismo-0.0.10.data/scripts/quickstart.py
granturismo-0.0.10.data/scripts/stream_position.py
granturismo-0.0.10.data/scripts/stream_suspension.py
granturismo-0.0.10.dist-info/METADATA
granturismo-0.0.10.dist-info/WHEEL
granturismo-0.0.10.dist-info/top_level.txt
granturismo-0.0.10.dist-info/RECORD
